<?xml version="1.0"?>
<ROOT>
	<FUNCTION_INFORMATION>
		<HAS_SIM_LIB VALUE="ON" />
	</FUNCTION_INFORMATION>
	<PARAMETERS>
		<PARAMETER NAME="power_up" TYPE="String" VALUE="low|high" DEFAULT_VALUE="low" />
		<PARAMETER NAME="invert_phase" TYPE="String" VALUE="false|true|dynamic" DEFAULT_VALUE="false" />
		<PARAMETER NAME="use_masterin" TYPE="String" VALUE="false|true" DEFAULT_VALUE="false" />
		<PARAMETER NAME="LPM_TYPE" TYPE="STRING" VALUE="stratixv_io_clock_divider" />
		<PARAMETER NAME="LPM_HINT" TYPE="STRING" VALUE="UNUSED" />
	</PARAMETERS>
	<PORTS>
		<PORT NAME="clk" TYPE="INPUT" DEFAULT_VALUE="0" />
		<PORT NAME="phaseinvertctrl" TYPE="INPUT" DEFAULT_VALUE="0" />
		<PORT NAME="masterin" TYPE="INPUT" DEFAULT_VALUE="0" />
		<PORT NAME="clkout" TYPE="OUTPUT" DEFAULT_VALUE="0" />
		<PORT NAME="slaveout" TYPE="OUTPUT" DEFAULT_VALUE="0" />
	</PORTS>
</ROOT>
